makefiles/__init__.py
makefiles/_version.py
makefiles/cli_parser.py
makefiles/exceptions.py
makefiles/mkfile.py
makefiles/types.py
makefiles/utils/__init__.py
makefiles/utils/cli_io.py
makefiles/utils/dirwalker.py
makefiles/utils/fileutils.py
makefiles/utils/picker/__init__.py
makefiles/utils/picker/fzf.py
makefiles/utils/picker/manual.py
makefiles_cli-1.0.0.data/scripts/mkfile
makefiles_cli-1.0.0.dist-info/licenses/LICENSE
makefiles_cli-1.0.0.dist-info/METADATA
makefiles_cli-1.0.0.dist-info/WHEEL
makefiles_cli-1.0.0.dist-info/top_level.txt
makefiles_cli-1.0.0.dist-info/RECORD
