Metadata-Version: 2.4
Name: makefiles-cli
Version: 1.0.0
Summary: A lightweight Python utility for file creation and template generation from XDG_TEMPLATES_DIR
License-Expression: GPL-3.0-only
Project-URL: Homepage, https://github.com/Rid1FZ/makefiles-cli
Keywords: makefiles,mkfiles,mkfile,makefiles-cli,mkfile-cli
Classifier: Programming Language :: Python :: 3.10
Classifier: Programming Language :: Python :: 3.11
Classifier: Programming Language :: Python :: 3.12
Classifier: Programming Language :: Python :: 3.13
Classifier: Operating System :: POSIX :: Linux
Classifier: Environment :: Console
Classifier: Typing :: Typed
Requires-Python: >=3.10
License-File: LICENSE
Dynamic: license-file
